py2sh/__init__.py
py2sh/helpstr.py
py2sh/py2sh.py
py2sh-0.0.3.dist-info/DESCRIPTION.rst
py2sh-0.0.3.dist-info/METADATA
py2sh-0.0.3.dist-info/RECORD
py2sh-0.0.3.dist-info/WHEEL
py2sh-0.0.3.dist-info/entry_points.txt
py2sh-0.0.3.dist-info/metadata.json
py2sh-0.0.3.dist-info/top_level.txt
