Metadata-Version: 2.0
Name: py2sh
Version: 0.0.3
Summary: A python CLI for busy scientists
Home-page: https://github.com/theideasmith/py2sh
Author: Akiva Lipshitz
Author-email: aclscientist@gmail.com
License: MIT
Download-URL: https://github.com/theideasmith/py2sh/archive/v0.0.3.tar.gz
Keywords: cli,command,argparse,click,script,function,bash,py2sh
Platform: UNKNOWN
